{
  "levels_order": ["CO", "FGHP", "SGHP", "HC", "MHC", "DH", "L2TH_PH", "UTH_RH"],
  "aliases": {
    "uth/rh": "UTH_RH",
    "uth": "UTH_RH",
    "rh": "UTH_RH",
    "l2th/ph": "L2TH_PH",
    "l2th": "L2TH_PH",
    "ph": "L2TH_PH",
    "dh": "DH",
    "mhc": "MHC",
    "hc": "HC",
    "sghp": "SGHP",
    "fghp": "FGHP",
    "co": "CO",
    "health center": "HC",
    "medicalized health center": "MHC",
    "district hospital": "DH",
    "provincial hospital": "L2TH_PH",
    "referral hospital": "UTH_RH"
  },
  "medications": {
    "amlodipine": ["HC", "MHC", "DH", "L2TH_PH", "UTH_RH"],
    "losartan": ["HC", "MHC", "DH", "L2TH_PH", "UTH_RH"],
    "hydrochlorothiazide": ["HC", "MHC", "DH", "L2TH_PH", "UTH_RH"],
    "hctz": ["HC", "MHC", "DH", "L2TH_PH", "UTH_RH"],
    "lisinopril": ["MHC", "DH", "L2TH_PH", "UTH_RH"],
    "enalapril": ["HC", "MHC", "DH", "L2TH_PH", "UTH_RH"],
    "methyldopa": ["HC", "MHC", "DH", "L2TH_PH", "UTH_RH"],
    "nifedipine": ["SGHP", "HC", "MHC", "DH", "L2TH_PH", "UTH_RH"],
    "furosemide": ["HC", "MHC", "DH", "L2TH_PH", "UTH_RH"],
    "spironolactone": ["HC", "MHC", "DH", "L2TH_PH", "UTH_RH"],
    "atenolol": ["HC", "MHC", "DH", "L2TH_PH", "UTH_RH"],
    "carvedilol": ["MHC", "DH", "L2TH_PH", "UTH_RH"],
    "hydralazine": ["MHC", "DH", "L2TH_PH", "UTH_RH"],
    "nicardipine": ["DH", "L2TH_PH", "UTH_RH"],
    "nitroprusside": ["L2TH_PH", "UTH_RH"],
    "labetalol": ["MHC", "DH", "L2TH_PH", "UTH_RH"],
    "clonidine": ["MHC", "DH", "L2TH_PH", "UTH_RH"],
    "candesartan": ["UTH_RH"],
    "metformin": ["HC", "MHC", "DH", "L2TH_PH", "UTH_RH"],
    "gliclazide": ["HC", "MHC", "DH", "L2TH_PH", "UTH_RH"],
    "glibenclamide": ["HC", "MHC", "DH", "L2TH_PH", "UTH_RH"],
    "glimepiride": ["MHC", "DH", "L2TH_PH", "UTH_RH"],
    "vildagliptin": ["HC", "MHC", "DH", "L2TH_PH", "UTH_RH"],
    "dapagliflozin": ["DH", "L2TH_PH", "UTH_RH"],
    "canagliflozin": ["DH", "L2TH_PH", "UTH_RH"],
    "insulin": ["HC", "MHC", "DH", "L2TH_PH", "UTH_RH"]
  }
}
